{"Heze":{"title":"Heze","lat":35.2333,"lng":115.4333,"byline":"Heze (菏泽, Hézé) is a city in Shandong.","edges":["Jinan","Zhengzhou","Henan","Xinxiang","Shanxian"]},"Hezhou":{"title":"Hezhou","lat":24.416388888889,"lng":111.54777777778,"byline":"Hezhou (贺州 Hè​zhōu​) is a city in Central Guangxi.","edges":["Guilin","Liuzhou","Longsheng","Guiyang","Mengshan"]},"Hezuo":{"title":"Hezuo","lat":34.99837,"lng":102.90999,"byline":"Hezuo (合作市 Hézuò; Tibetan: གཙོས་གྲོང་ཁྱིར། Zö) is a town in Gansu Province.","edges":["Lanzhou","Xining","Linxia","Xiahe","Aba (China)","Ruoergai","Sichuan","Langmusi"]}}