{"McAlester":{"title":"McAlester","lat":34.933056,"lng":-95.766389,"byline":"McAlester is in the Choctaw Country region of Oklahoma and home to the Oklahoma State Penitentiary.","edges":["Talihina","Oklahoma","Mena (Arkansas)","Arkansas"]},"McAllen":{"title":"McAllen","lat":26.216389,"lng":-98.236389,"byline":"McAllen, the City of Palms, is in the southern plains of Texas, USA.","edges":["Reynosa","Harlingen (Texas)","Brownsville (Texas)","South Padre Island","Kingsville (Texas)","Laredo","Tampico"]}}