{"Obuse":{"title":"Obuse","lat":36.7,"lng":138.316667,"byline":"Obuse is a town in Nagano Prefecture.","edges":["Kusatsu","Nagano","Chikuma","Yamanouchi","Joshin'etsukogen National Park","Matsumoto","Kiso Valley","Hakuba","Azumino"]},"Obudu":{"title":"Obudu","lat":6.666667,"lng":9.166667,"byline":"Obudu is a local government area in Cross River State in South South Nigeria.","edges":["Boki","Ikom","Benue State","Obubra","Agbokim Waterfalls"]},"Obubra":{"title":"Obubra","lat":6.08333,"lng":8.33333,"byline":"Obubra is a local government area in Cross River State, South South Nigeria.","edges":["Ikom","Boki","Ogoja","Obudu"]}}