{"Rwanda":{"title":"Rwanda","lat":-1.9,"lng":29.8,"byline":"Rwanda is a relatively stable East African country, and easily accessible from Kenya and Uganda.","edges":["Kabale","Kampala","Mwanza"]},"Rwaihamba":{"title":"Rwaihamba","lat":0.505,"lng":30.29805,"byline":"Rwaihamba is a village in Western Uganda, 40 km from Fort Portal.","edges":["Fort Portal"]},"Rwamagana":{"title":"Rwamagana","lat":-1.9525,"lng":30.437778,"byline":"Rwamagana is the capital of the Rwamagana District and Rwanda's Eastern Province.","edges":["Akagera National Park"]}}