{"Upcountry Árnessýsla":{"title":"Upcountry Árnessýsla","lat":64.198,"lng":-20.359,"byline":"Upcountry Árnessýsla, or Uppsveitir Árnessýslu in Icelandic, is a rural area in South Iceland, home to many of the country's most famous attractions.","edges":["Selfoss"]},"Upcountry South Carolina":{"title":"Upcountry South Carolina","lat":34.7167,"lng":-82.1833,"byline":"Upcountry South Carolina, also known as The Upstate, consists of the northwestern corner of the state.","edges":["North Carolina Mountains","Charlotte","Atlanta","Asheville"]}}